grasshopper/__init__.py
grasshopper/lib/__init__.py
grasshopper/lib/grasshopper.py
grasshopper/lib/configuration/__init__.py
grasshopper/lib/configuration/gh_configuration.py
grasshopper/lib/fixtures/__init__.py
grasshopper/lib/fixtures/grasshopper_constants.py
grasshopper/lib/journeys/__init__.py
grasshopper/lib/journeys/base_journey.py
grasshopper/lib/journeys/temp_gh_composite.py
grasshopper/lib/reporting/__init__.py
grasshopper/lib/reporting/er_basic_console_reporter.py
grasshopper/lib/reporting/iextendedreporter.py
grasshopper/lib/reporting/reporter_extensions.py
grasshopper/lib/reporting/shared_reporting.py
grasshopper/lib/util/__init__.py
grasshopper/lib/util/check_constants.py
grasshopper/lib/util/decorators.py
grasshopper/lib/util/launch.py
grasshopper/lib/util/listeners.py
grasshopper/lib/util/metrics.py
grasshopper/lib/util/shapes.py
grasshopper/lib/util/utils.py
locust_grasshopper-2.1.2.dist-info/licenses/LICENSE
locust_grasshopper-2.1.2.dist-info/METADATA
locust_grasshopper-2.1.2.dist-info/WHEEL
locust_grasshopper-2.1.2.dist-info/entry_points.txt
locust_grasshopper-2.1.2.dist-info/top_level.txt
locust_grasshopper-2.1.2.dist-info/RECORD
