Metadata-Version: 2.4
Name: locust-grasshopper
Version: 2.1.2
Summary: a load testing tool extended from locust
Author-email: "Alteryx, Inc." <open_source_support@alteryx.com>
Maintainer-email: "Alteryx, Inc." <open_source_support@alteryx.com>
License:                                  Apache License
Project-URL: repository, https://github.com/alteryx/locust-grasshopper
Keywords: load testing,performance,locust,grasshopper
Classifier: License :: OSI Approved :: Apache Software License
Classifier: Programming Language :: Python :: 3.10
Classifier: Programming Language :: Python :: 3.11
Classifier: Operating System :: OS Independent
Classifier: Intended Audience :: Developers
Classifier: Intended Audience :: System Administrators
Classifier: Topic :: Software Development :: Testing
Classifier: Topic :: Software Development :: Testing :: Traffic Generation
Classifier: Topic :: System :: Distributed Computing
Classifier: Framework :: Pytest
Requires-Python: <4,>=3.10
License-File: LICENSE
Requires-Dist: gevent>=24.2.1
Requires-Dist: influxdb>=5.3.1
Requires-Dist: locust~=2.23
Requires-Dist: locust-influxdb-listener~=1.0
Requires-Dist: pytest>=6.2.5
Requires-Dist: pyyaml>=5.4.1
Requires-Dist: tag-matcher>=0.0.5
Requires-Dist: termcolor~=1.0
Provides-Extra: dev
Requires-Dist: assertpy==1.1; extra == "dev"
Requires-Dist: pytest-cov==4.0.0; extra == "dev"
Requires-Dist: pytest-mock==3.10.0; extra == "dev"
Requires-Dist: requests-mock==1.11.0; extra == "dev"
Requires-Dist: tox==4.13.0; extra == "dev"
Requires-Dist: ruff==0.2.2; extra == "dev"
Dynamic: license-file
